qlot/__init__.py
qlot/qlot.py
qlot-0.1.0.dist-info/LICENSE
qlot-0.1.0.dist-info/METADATA
qlot-0.1.0.dist-info/WHEEL
qlot-0.1.0.dist-info/RECORD
